dummy_test_plugin/__init__.py
dummy_test_plugin/_version.py
dummy_test_plugin-0.1.3.dist-info/LICENSE
dummy_test_plugin-0.1.3.dist-info/METADATA
dummy_test_plugin-0.1.3.dist-info/WHEEL
dummy_test_plugin-0.1.3.dist-info/entry_points.txt
dummy_test_plugin-0.1.3.dist-info/top_level.txt
dummy_test_plugin-0.1.3.dist-info/RECORD
