Metadata-Version: 2.1
Name: dummy-test-plugin
Version: 0.1.3
Summary: A simple plugin for testing purposes
Author: napari team
License: BSD-3-Clause
License-File: LICENSE
Requires-Dist: magicgui
Requires-Dist: napari
Requires-Dist: napari-plugin-engine >=0.1.4
Requires-Dist: numpy
Requires-Dist: qtpy
